MoCV/__init__.py
MoCV/contrastImage.py
MoCV/geom_transform.py
MoCV/histogram.py
MoCV/image_function.py
MoCV/linear_scale_image.py
MoCV/pixel.py
MoCV/segmentation.py
lib/Histogram.py
lib/__init__.py
MoCV-0.1.0.dist-info/LICENSE
MoCV-0.1.0.dist-info/METADATA
MoCV-0.1.0.dist-info/WHEEL
MoCV-0.1.0.dist-info/top_level.txt
MoCV-0.1.0.dist-info/RECORD
