Metadata-Version: 2.1
Name: MoCV
Version: 0.1.0
Summary: List and details of Computer Vision algorithms
Home-page: https://github.com/quocdat32461997/MoCV
Author: datqngo
Author-email: quocdat32461997@yahoo.com
License: UNKNOWN
Platform: UNKNOWN
Classifier: Programming Language :: Python :: 3
Classifier: License :: OSI Approved :: MIT License
Classifier: Operating System :: OS Independent
Requires-Dist: numpy
Requires-Dist: matplotlib
Requires-Dist: opencv-python
